ezRL/__init__.py
ezRL/test.py
ezRL/parts/episode.py
ezRL/parts/history.py
ezRL/parts/utils.py
ezRL/parts/DQN_Agent/__init__.py
ezRL/parts/DQN_Agent/test.py
ezRL/parts/DQN_Agent/parts/playlog.py
ezRL/parts/DQN_Agent/parts/policy.py
ezRL/parts/DQN_Agent/parts/target_twin.py
ezRL/parts/DQN_Agent/parts/test_agent.py
ezRL/parts/DQN_Agent/parts/train_qnet.py
ezRL/parts/DQN_Agent/parts/trigger.py
ezRL/parts/DQN_Agent/parts/utils.py
ezRL/parts/browser_arena/__init__.py
ezRL/parts/browser_arena/test.py
ezRL/parts/catcher_game/__init__.py
ezRL/parts/catcher_game/history2img.py
ezRL/parts/catcher_game/test.py
ezRL/parts/debug_players/__init__.py
ezRL/parts/debug_players/test.py
ezRL/parts/demo/__init__.py
ezRL/parts/normal_cnn/__init__.py
ezRL/parts/normal_cnn/test.py
ezRL/parts/normal_cnn/parts/utils.py
ezRL/parts/old/dqn/__init__.py
ezRL/parts/old/old_normal_cnn/__init__.py
ezRL/parts/old/old_normal_cnn/test.py
ezRL/parts/rw_game/__init__.py
ezRL/parts/rw_game/test.py
ezRL-1.7.5.dist-info/METADATA
ezRL-1.7.5.dist-info/WHEEL
ezRL-1.7.5.dist-info/top_level.txt
ezRL-1.7.5.dist-info/RECORD
