Metadata-Version: 2.1
Name: ezRL
Version: 1.7.5
Summary: easy Reinforcement Learning tool for python
Home-page: https://github.co.jp/
Author: ezRL_team
Author-email: ezrl.adm@gmail.com
License: CC0 v1.0
Platform: UNKNOWN
Classifier: Programming Language :: Python :: 3
Classifier: Topic :: Software Development :: Libraries
Classifier: License :: CC0 1.0 Universal (CC0 1.0) Public Domain Dedication
Requires-Dist: relpath
Requires-Dist: sout
Requires-Dist: resout
Requires-Dist: fies
